MANIFEST.in
README.md
setup.cfg
setup.py
qchaindym_ta/__init__.py
qchaindym_ta/main.py
qchaindym_ta.egg-info/PKG-INFO
qchaindym_ta.egg-info/SOURCES.txt
qchaindym_ta.egg-info/dependency_links.txt
qchaindym_ta.egg-info/top_level.txt
qchaindym_ta/__pycache__/__init__.cpython-311.pyc
qchaindym_ta/__pycache__/cycle_indicators.cpython-311.pyc
qchaindym_ta/__pycache__/ma.cpython-311.pyc
qchaindym_ta/__pycache__/main.cpython-311.pyc
qchaindym_ta/__pycache__/momentum_indicators.cpython-311.pyc
qchaindym_ta/__pycache__/overlap_studies.cpython-311.pyc
qchaindym_ta/__pycache__/rma.cpython-311.pyc
qchaindym_ta/__pycache__/util.cpython-311.pyc
qchaindym_ta/candles/__init__.py
qchaindym_ta/cycles/__init__.py
qchaindym_ta/momentum/__init__.py
qchaindym_ta/overlap/__init__.py
qchaindym_ta/performance/__init__.py
qchaindym_ta/statistics/__init__.py
qchaindym_ta/trend/__init__.py
qchaindym_ta/utils/__init__.py
qchaindym_ta/utils/_candles.py
qchaindym_ta/utils/_core.py
qchaindym_ta/utils/_math.py
qchaindym_ta/utils/_metrics.py
qchaindym_ta/utils/_signals.py
qchaindym_ta/utils/_time.py
qchaindym_ta/utils/__pycache__/__init__.cpython-311.pyc
qchaindym_ta/utils/__pycache__/_candles.cpython-311.pyc
qchaindym_ta/utils/__pycache__/_core.cpython-311.pyc
qchaindym_ta/utils/__pycache__/_math.cpython-311.pyc
qchaindym_ta/utils/__pycache__/_metrics.cpython-311.pyc
qchaindym_ta/utils/__pycache__/_signals.cpython-311.pyc
qchaindym_ta/utils/__pycache__/_time.cpython-311.pyc
qchaindym_ta/volatility/__init__.py
qchaindym_ta/volume/__init__.py