Metadata-Version: 2.1
Name: qchaindym_ta
Version: 0.1
Summary: 一个数字货币指标分析库
Home-page: https://gitee.com/yu-chiu/QchainDym
Author: YU CHIU
Author-email: yu.chiu@foxmail.com
License: BSD-3-Clause  # Example license
Classifier: License :: OSI Approved :: BSD License
Classifier: Operating System :: OS Independent
Classifier: Programming Language :: Python
Classifier: Programming Language :: Python :: 3
Classifier: Programming Language :: Python :: 3 :: Only
Classifier: Programming Language :: Python :: 3.10
Classifier: Programming Language :: Python :: 3.11
Classifier: Programming Language :: Python :: 3.12
Classifier: Topic :: Internet :: WWW/HTTP
Classifier: Topic :: Internet :: WWW/HTTP :: Dynamic Content
Requires-Python: >=3.10
